datanorm/__init__.py
datanorm/datanorm_files.py
datanorm/datanorm_item.py
datanorm-0.0.2a0.dist-info/LICENSE
datanorm-0.0.2a0.dist-info/METADATA
datanorm-0.0.2a0.dist-info/WHEEL
datanorm-0.0.2a0.dist-info/top_level.txt
datanorm-0.0.2a0.dist-info/RECORD
